midas_client/__init__.py
midas_client/config.py
midas_client/io.py
midas_client/logging_config.py
midas_client/midas.py
midas_client/session.py
midas_client/settings.json
uk_midas_client-0.602.dist-info/licenses/LICENSE
uk_midas_client-0.602.dist-info/METADATA
uk_midas_client-0.602.dist-info/WHEEL
uk_midas_client-0.602.dist-info/top_level.txt
uk_midas_client-0.602.dist-info/RECORD
