Metadata-Version: 2.4
Name: uk-midas-client
Version: 0.602
Summary: A Python client for UK Met Office MIDAS via CEDA Archives
Home-page: https://github.com/katielocks/uk_midas_client
Author: Katherine Whitelock
Author-email: ktwhitelock@outlook.com
Classifier: Programming Language :: Python :: 3
Classifier: License :: OSI Approved :: MIT License
Classifier: Operating System :: OS Independent
Requires-Python: >=3.10
License-File: LICENSE
Requires-Dist: numpy==2.3.0
Requires-Dist: pandas==2.3.0
Requires-Dist: pytest==8.4.0
Requires-Dist: Requests==2.32.4
Requires-Dist: scikit_learn==1.7.0
Requires-Dist: setuptools==80.8.0
Dynamic: author
Dynamic: author-email
Dynamic: classifier
Dynamic: description
Dynamic: description-content-type
Dynamic: home-page
Dynamic: license-file
Dynamic: requires-dist
Dynamic: requires-python
Dynamic: summary
